fabric_cli/__init__.py
fabric_cli/main.py
fabric_cli/client/__init__.py
fabric_cli/client/fab_api_azure.py
fabric_cli/client/fab_api_capacity.py
fabric_cli/client/fab_api_client.py
fabric_cli/client/fab_api_connection.py
fabric_cli/client/fab_api_domain.py
fabric_cli/client/fab_api_folders.py
fabric_cli/client/fab_api_gateway.py
fabric_cli/client/fab_api_item.py
fabric_cli/client/fab_api_jobs.py
fabric_cli/client/fab_api_labels.py
fabric_cli/client/fab_api_managedidentity.py
fabric_cli/client/fab_api_managedprivateendpoint.py
fabric_cli/client/fab_api_mirroring.py
fabric_cli/client/fab_api_onelake.py
fabric_cli/client/fab_api_shortcuts.py
fabric_cli/client/fab_api_sparkpool.py
fabric_cli/client/fab_api_tables.py
fabric_cli/client/fab_api_types.py
fabric_cli/client/fab_api_utils.py
fabric_cli/client/fab_api_workspace.py
fabric_cli/commands/__init__.py
fabric_cli/commands/acls/__init__.py
fabric_cli/commands/acls/fab_acls.py
fabric_cli/commands/acls/fab_acls_get.py
fabric_cli/commands/acls/fab_acls_ls.py
fabric_cli/commands/acls/fab_acls_rm.py
fabric_cli/commands/acls/fab_acls_set.py
fabric_cli/commands/api/__init__.py
fabric_cli/commands/api/fab_api.py
fabric_cli/commands/api/fab_api_request.py
fabric_cli/commands/auth/__init__.py
fabric_cli/commands/auth/fab_auth.py
fabric_cli/commands/config/__init__.py
fabric_cli/commands/config/fab_config.py
fabric_cli/commands/config/fab_config_clear_cache.py
fabric_cli/commands/config/fab_config_get.py
fabric_cli/commands/config/fab_config_ls.py
fabric_cli/commands/config/fab_config_set.py
fabric_cli/commands/fs/__init__.py
fabric_cli/commands/fs/fab_fs.py
fabric_cli/commands/fs/fab_fs_assign.py
fabric_cli/commands/fs/fab_fs_cd.py
fabric_cli/commands/fs/fab_fs_cp.py
fabric_cli/commands/fs/fab_fs_exists.py
fabric_cli/commands/fs/fab_fs_export.py
fabric_cli/commands/fs/fab_fs_get.py
fabric_cli/commands/fs/fab_fs_import.py
fabric_cli/commands/fs/fab_fs_ln.py
fabric_cli/commands/fs/fab_fs_ls.py
ms_fabric_cli-1.3.1.dist-info/licenses/LICENSE
ms_fabric_cli-1.3.1.dist-info/licenses/NOTICE.txt
ms_fabric_cli-1.3.1.dist-info/METADATA
ms_fabric_cli-1.3.1.dist-info/WHEEL
ms_fabric_cli-1.3.1.dist-info/entry_points.txt
ms_fabric_cli-1.3.1.dist-info/top_level.txt
ms_fabric_cli-1.3.1.dist-info/RECORD
