Metadata-Version: 2.4
Name: ms-fabric-cli
Version: 1.3.1
Summary: Command-line tool for Microsoft Fabric
Author: Microsoft Corporation
License-Expression: MIT
Classifier: Programming Language :: Python :: 3
Classifier: Programming Language :: Python :: 3.10
Classifier: Programming Language :: Python :: 3.11
Classifier: Programming Language :: Python :: 3.12
Classifier: Operating System :: OS Independent
Requires-Python: <3.13,>=3.10
License-File: LICENSE
License-File: NOTICE.txt
Requires-Dist: msal[broker]<2,>=1.29
Requires-Dist: msal_extensions
Requires-Dist: questionary
Requires-Dist: prompt_toolkit>=3.0.41
Requires-Dist: cachetools>=5.5.0
Requires-Dist: jmespath
Requires-Dist: pyyaml==6.0.2
Requires-Dist: argcomplete>=3.6.2
Requires-Dist: psutil==7.0.0
Provides-Extra: test
Requires-Dist: pytest>=8.2.1; extra == "test"
Dynamic: license-file
